tmdb/__init__.py
tmdb/client.py
tmdb/core/__init__.py
tmdb/core/api_error.py
tmdb/core/client_wrapper.py
tmdb/core/datetime_utils.py
tmdb/core/file.py
tmdb/core/force_multipart.py
tmdb/core/http_client.py
tmdb/core/http_response.py
tmdb/core/jsonable_encoder.py
tmdb/core/pydantic_utilities.py
tmdb/core/query_encoder.py
tmdb/core/remove_none_from_dict.py
tmdb/core/request_options.py
tmdb/core/serialization.py
tmdb/environment.py
tmdb/py.typed
tmdb/raw_client.py
tmdb/types/__init__.py
tmdb/types/account_favorite_movies_request_sort_by.py
tmdb/types/account_favorite_movies_response.py
tmdb/types/account_favorite_movies_response_results_item.py
tmdb/types/account_favorite_tv_request_sort_by.py
tmdb/types/account_favorite_tv_response.py
tmdb/types/account_favorite_tv_response_results_item.py
tmdb/types/account_lists_response.py
tmdb/types/account_lists_response_results_item.py
tmdb/types/account_movie_recommendations_response.py
tmdb/types/account_movie_recommendations_response_results_item.py
tmdb/types/account_movie_watchlist_request_sort_by.py
tmdb/types/account_movie_watchlist_response.py
tmdb/types/account_movie_watchlist_response_results_item.py
tmdb/types/account_rated_movies_request_sort_by.py
tmdb/types/account_rated_movies_response.py
tmdb/types/account_rated_movies_response_results_item.py
tmdb/types/account_rated_movies_response_results_item_account_rating.py
tmdb/types/account_rated_tv_request_sort_by.py
tmdb/types/account_rated_tv_response.py
tmdb/types/account_rated_tv_response_results_item.py
tmdb/types/account_rated_tv_response_results_item_account_rating.py
tmdb/types/account_tv_recommendations_response.py
tmdb/types/account_tv_recommendations_response_results_item.py
tmdb/types/account_tv_watchlist_request_sort_by.py
tmdb/types/account_tv_watchlist_response.py
tmdb/types/account_tv_watchlist_response_results_item.py
tmdb/types/auth_create_access_token_response.py
tmdb/types/auth_create_request_token_response.py
tmdb/types/auth_logout_response.py
tmdb_ryanstep-1.0.0.dist-info/METADATA
tmdb_ryanstep-1.0.0.dist-info/WHEEL
tmdb_ryanstep-1.0.0.dist-info/RECORD
